Metadata-Version: 1.0
Name: ptfutils
Version: 0.0.12
Summary: Useful modules for tensorflow
Home-page: https://github.com/PiotrDabkowski/
Author: Piotr Dabkowski
Author-email: piodrus@gmail.com
License: MIT
Platform: UNKNOWN
